deeputilities/__init__.py
deeputilities/client/__init__.py
deeputilities/client/commands/__init__.py
deeputilities/client/commands/config_maker_command.py
deeputilities/client/commands/demo_command.py
deeputilities/client/commands/diagnosis_command.py
deeputilities/client/commands/fullrun_command.py
deeputilities/client/commands/ingest_command.py
deeputilities/client/deeputils_app.py
deeputilities/client/options/__init__.py
deeputilities/client/options/options.py
deeputilities/configuration/__init__.py
deeputilities/configuration/configuration_object.py
deeputilities/configuration/example_config.yaml
deeputilities/configuration/yaml_functions.py
deeputilities/diagnosis/__init__.py
deeputilities/diagnosis/diagnose.py
deeputilities/diagnosis/diagnostics.py
deeputilities/ingest/__init__.py
deeputilities/ingest/custom_dataset.py
deeputilities/ingest/datasets/__init__.py
deeputilities/ingest/datasets/h5_dataset.py
deeputilities/ingest/datasets/image.py
deeputilities/ingest/datasets/image_dataset.py
deeputilities/ingest/datasets/numpy_dataset.py
deeputilities/ingest/ingestion.py
deeputilities/ingest/ingestor.py
deeputilities/model/__init__.py
deeputilities/model/architecture_search.py
deeputilities/model/deep_learning_models.py
deeputilities/model/lazy_neural_network.py
deeputilities/model/model.py
deeputilities/preprocess/__init__.py
deeputilities/preprocess/preprocess.py
deeputilities/preprocess/preprocessor.py
deeputilities/preprocess/preprocessor_core.py
deeputilities/settings.py
deeputilities/stand_in_pkg/deepbench.py
deeputilities/stand_in_pkg/deepgotdata.py
deeputilities-0.1.1.dist-info/METADATA
deeputilities-0.1.1.dist-info/WHEEL
deeputilities-0.1.1.dist-info/entry_points.txt
deeputilities-0.1.1.dist-info/RECORD
